{
  "Name": "PatternMaker",
  "Notes": "From: https://drive.google.com/file/d/1rNQm-FwAHJaX1HRQW86sQzm_GyZaPxPB/view",
  "jsonColorMap": [
    {
      "Key": {
        "PaletteType": "DMC",
        "ID": "150",
        "Name": "Dusty Rose - Ultra Very Dark"
      },
      "Value": {
        "Argb": -6342587,
        "Hex": "9F3845"
      }
    },
    {
      "Key": {
        "PaletteType": "DMC",
        "ID": "151",
        "Name": "Dusty Rose - Ultra Light"
      },
      "Value": {
        "Argb": -869179,
        "Hex": "F2BCC5"
      }
    },
    {
      "Key": {
        "PaletteType": "DMC",
        "ID": "152",
        "Name": "Tawny - Dark"
      },
      "Value": {
        "Argb": -3169642,
        "Hex": "CFA296"
      }
    },
    {
      "Key": {
        "PaletteType": "DMC",
        "ID": "153",
        "Name": "Lilac"
      },
      "Value": {
        "Argb": -2179879,
        "Hex": "DEBCD9"
      }
    },
    {
      "Key": {
        "PaletteType": "DMC",
        "ID": "154",
        "Name": "Red - Very Dark"
      },
      "Value": {
        "Argb": -11719107,
        "Hex": "4D2E3D"
      }
    },
    {
      "Key": {
        "PaletteType": "DMC",
        "ID": "155",
        "Name": "Forget-me-not Blue"
      },
      "Value": {
        "Argb": -7304253,
        "Hex": "908BC3"
      }
    },
    {
      "Key": {
        "PaletteType": "DMC",
        "ID": "156",
        "Name": "Blue - Medium"
      },
      "Value": {
        "Argb": -7628091,
        "Hex": "8B9AC5"
      }
    },
    {
      "Key": {
        "PaletteType": "DMC",
        "ID": "157",
        "Name": "Blue - Light"
      },
      "Value": {
        "Argb": -5520674,
        "Hex": "ABC2DE"
      }
    },
    {
      "Key": {
        "PaletteType": "DMC",
        "ID": "158",
        "Name": "Blue - Dark"
      },
      "Value": {
        "Argb": -12169086,
        "Hex": "465082"
      }
    },
    {
      "Key": {
        "PaletteType": "DMC",
        "ID": "159",
        "Name": "Petrol Blue - Light"
      },
      "Value": {
        "Argb": -5786419,
        "Hex": "A7B4CD"
      }
    },
    {
      "Key": {
        "PaletteType": "DMC",
        "ID": "160",
        "Name": "Petrol Blue - Medium"
      },
      "Value": {
        "Argb": -8220498,
        "Hex": "8290AE"
      }
    },
    {
      "Key": {
        "PaletteType": "DMC",
        "ID": "161",
        "Name": "Petrol Blue - Dark"
      },
      "Value": {
        "Argb": -10062444,
        "Hex": "667594"
      }
    },
    {
      "Key": {
        "PaletteType": "DMC",
        "ID": "162",
        "Name": "Blue - Ultra Very Light"
      },
      "Value": {
        "Argb": -4334618,
        "Hex": "BDDBE6"
      }
    },
    {
      "Key": {
        "PaletteType": "DMC",
        "ID": "163",
        "Name": "Celadon Green - Medium"
      },
      "Value": {
        "Argb": -11102863,
        "Hex": "569571"
      }
    },
    {
      "Key": {
        "PaletteType": "DMC",
        "ID": "164",
        "Name": "Green - Light"
      },
      "Value": {
        "Argb": -6304627,
        "Hex": "9FCC8D"
      }
    },
    {
      "Key": {
        "PaletteType": "DMC",
        "ID": "165",
        "Name": "Green - Bright"
      },
      "Value": {
        "Argb": -2434952,
        "Hex": "DAD878"
      }
    },
    {
      "Key": {
        "PaletteType": "DMC",
        "ID": "166",
        "Name": "Moss Green - Medium Light"
      },
      "Value": {
        "Argb": -4211936,
        "Hex": "BFBB20"
      }
    },
    {
      "Key": {
        "PaletteType": "DMC",
        "ID": "167",
        "Name": "Khaki Brown"
      },
      "Value": {
        "Argb": -6323129,
        "Hex": "9F8447"
      }
    },
    {
      "Key": {
        "PaletteType": "DMC",
        "ID": "168",
        "Name": "Silver Gray"
      },
      "Value": {
        "Argb": -4930623,
        "Hex": "B4C3C1"
      }
    },
    {
      "Key": {
        "PaletteType": "DMC",
        "ID": "169",
        "Name": "Pewter Gray - Light"
      },
      "Value": {
        "Argb": -7628140,
        "Hex": "8B9A94"
      }
    },
    {
      "Key": {
        "PaletteType": "DMC",
        "ID": "208",
        "Name": "Lavender - Very Dark"
      },
      "Value": {
        "Argb": -6786900,
        "Hex": "9870AC"
      }
    },
    {
      "Key": {
        "PaletteType": "DMC",
        "ID": "209",
        "Name": "Lavender - Dark"
      },
      "Value": {
        "Argb": -4811837,
        "Hex": "B693C3"
      }
    },
    {
      "Key": {
        "PaletteType": "DMC",
        "ID": "210",
        "Name": "Lavender - Medium"
      },
      "Value": {
        "Argb": -3559459,
        "Hex": "C9AFDD"
      }
    },
    {
      "Key": {
        "PaletteType": "DMC",
        "ID": "211",
        "Name": "Lavender - Light"
      },
      "Value": {
        "Argb": -2833436,
        "Hex": "D4C3E4"
      }
    },
    {
      "Key": {
        "PaletteType": "DMC",
        "ID": "221",
        "Name": "Shell Pink - Very Dark"
      },
      "Value": {
        "Argb": -7847368,
        "Hex": "884238"
      }
    },
    {
      "Key": {
        "PaletteType": "DMC",
        "ID": "223",
        "Name": "Shell Pink - Light"
      },
      "Value": {
        "Argb": -4488837,
        "Hex": "BB817B"
      }
    },
    {
      "Key": {
        "PaletteType": "DMC",
        "ID": "224",
        "Name": "Shell Pink - Very Light"
      },
      "Value": {
        "Argb": -2116698,
        "Hex": "DFB3A6"
      }
    },
    {
      "Key": {
        "PaletteType": "DMC",
        "ID": "225",
        "Name": "Shell Pink - Ultra Very Light"
      },
      "Value": {
        "Argb": -1254961,
        "Hex": "ECD9CF"
      }
    },
    {
      "Key": {
        "PaletteType": "DMC",
        "ID": "300",
        "Name": "Mahogany - Very Dark"
      },
      "Value": {
        "Argb": -8892892,
        "Hex": "784E24"
      }
    },
    {
      "Key": {
        "PaletteType": "DMC",
        "ID": "301",
        "Name": "Mahogany - Medium"
      },
      "Value": {
        "Argb": -5609680,
        "Hex": "AA6730"
      }
    },
    {
      "Key": {
        "PaletteType": "DMC",
        "ID": "304",
        "Name": "Red - Medium"
      },
      "Value": {
        "Argb": -6409422,
        "Hex": "9E3332"
      }
    },
    {
      "Key": {
        "PaletteType": "DMC",
        "ID": "307",
        "Name": "Lemon"
      },
      "Value": {
        "Argb": -597231,
        "Hex": "F6E311"
      }
    },
    {
      "Key": {
        "PaletteType": "DMC",
        "ID": "309",
        "Name": "Rose - Dark"
      },
      "Value": {
        "Argb": -4701359,
        "Hex": "B84351"
      }
    },
    {
      "Key": {
        "PaletteType": "DMC",
        "ID": "310",
        "Name": "Black"
      },
      "Value": {
        "Argb": -13880795,
        "Hex": "2C3225"
      }
    },
    {
      "Key": {
        "PaletteType": "DMC",
        "ID": "311",
        "Name": "Blue - Medium"
      },
      "Value": {
        "Argb": -13610897,
        "Hex": "30506F"
      }
    },
    {
      "Key": {
        "PaletteType": "DMC",
        "ID": "312",
        "Name": "Baby Blue - Very Dark"
      },
      "Value": {
        "Argb": -13082231,
        "Hex": "386189"
      }
    },
    {
      "Key": {
        "PaletteType": "DMC",
        "ID": "315",
        "Name": "Antique Mauve - Medium Dark"
      },
      "Value": {
        "Argb": -7447204,
        "Hex": "8E5D5C"
      }
    },
    {
      "Key": {
        "PaletteType": "DMC",
        "ID": "316",
        "Name": "Antique Mauve - Medium"
      },
      "Value": {
        "Argb": -4224868,
        "Hex": "BF889C"
      }
    },
    {
      "Key": {
        "PaletteType": "DMC",
        "ID": "317",
        "Name": "Pewter Gray"
      },
      "Value": {
        "Argb": -9866635,
        "Hex": "697275"
      }
    },
    {
      "Key": {
        "PaletteType": "DMC",
        "ID": "318",
        "Name": "Steel Gray - Light"
      },
      "Value": {
        "Argb": -6248528,
        "Hex": "A0A7B0"
      }
    },
    {
      "Key": {
        "PaletteType": "DMC",
        "ID": "319",
        "Name": "Pistachio Green - Very Dark"
      },
      "Value": {
        "Argb": -13278403,
        "Hex": "35633D"
      }
    },
    {
      "Key": {
        "PaletteType": "DMC",
        "ID": "320",
        "Name": "Pistachio Green - Medium"
      },
      "Value": {
        "Argb": -9330574,
        "Hex": "71A072"
      }
    },
    {
      "Key": {
        "PaletteType": "DMC",
        "ID": "321",
        "Name": "Red"
      },
      "Value": {
        "Argb": -5167318,
        "Hex": "B1272A"
      }
    },
    {
      "Key": {
        "PaletteType": "DMC",
        "ID": "322",
        "Name": "Baby Blue"
      },
      "Value": {
        "Argb": -10977105,
        "Hex": "5880AF"
      }
    },
    {
      "Key": {
        "PaletteType": "DMC",
        "ID": "326",
        "Name": "Rose - Very Dark"
      },
      "Value": {
        "Argb": -5688002,
        "Hex": "A9353E"
      }
    },
    {
      "Key": {
        "PaletteType": "DMC",
        "ID": "327",
        "Name": "Violet"
      },
      "Value": {
        "Argb": -8759945,
        "Hex": "7A5577"
      }
    },
    {
      "Key": {
        "PaletteType": "DMC",
        "ID": "333",
        "Name": "Blue Violet - Very Dark"
      },
      "Value": {
        "Argb": -9542489,
        "Hex": "6E64A7"
      }
    },
    {
      "Key": {
        "PaletteType": "DMC",
        "ID": "334",
        "Name": "Baby Blue - Medium"
      },
      "Value": {
        "Argb": -9594691,
        "Hex": "6D98BD"
      }
    },
    {
      "Key": {
        "PaletteType": "DMC",
        "ID": "335",
        "Name": "Rose"
      },
      "Value": {
        "Argb": -2594437,
        "Hex": "D8697B"
      }
    },
    {
      "Key": {
        "PaletteType": "DMC",
        "ID": "336",
        "Name": "Blue"
      },
      "Value": {
        "Argb": -13351327,
        "Hex": "344661"
      }
    },
    {
      "Key": {
        "PaletteType": "DMC",
        "ID": "340",
        "Name": "Blue Violet - Medium"
      },
      "Value": {
        "Argb": -6775084,
        "Hex": "989ED4"
      }
    },
    {
      "Key": {
        "PaletteType": "DMC",
        "ID": "341",
        "Name": "Blue Violet - Light"
      },
      "Value": {
        "Argb": -5522213,
        "Hex": "ABBCDB"
      }
    },
    {
      "Key": {
        "PaletteType": "DMC",
        "ID": "347",
        "Name": "Salmon - Very Dark"
      },
      "Value": {
        "Argb": -4305854,
        "Hex": "BE4C42"
      }
    },
    {
      "Key": {
        "PaletteType": "DMC",
        "ID": "349",
        "Name": "Coral - Dark"
      },
      "Value": {
        "Argb": -4050639,
        "Hex": "C23131"
      }
    },
    {
      "Key": {
        "PaletteType": "DMC",
        "ID": "350",
        "Name": "Coral - Medium"
      },
      "Value": {
        "Argb": -2335925,
        "Hex": "DC5B4B"
      }
    },
    {
      "Key": {
        "PaletteType": "DMC",
        "ID": "351",
        "Name": "Coral"
      },
      "Value": {
        "Argb": -1673117,
        "Hex": "E67863"
      }
    },
    {
      "Key": {
        "PaletteType": "DMC",
        "ID": "352",
        "Name": "Coral - Light"
      },
      "Value": {
        "Argb": -743024,
        "Hex": "F4A990"
      }
    },
    {
      "Key": {
        "PaletteType": "DMC",
        "ID": "353",
        "Name": "Peach"
      },
      "Value": {
        "Argb": -865612,
        "Hex": "F2CAB4"
      }
    },
    {
      "Key": {
        "PaletteType": "DMC",
        "ID": "355",
        "Name": "Terra Cotta - Dark"
      },
      "Value": {
        "Argb": -6402247,
        "Hex": "9E4F39"
      }
    },
    {
      "Key": {
        "PaletteType": "DMC",
        "ID": "356",
        "Name": "Terra Cotta - Medium"
      },
      "Value": {
        "Argb": -4097443,
        "Hex": "C17A5D"
      }
    },
    {
      "Key": {
        "PaletteType": "DMC",
        "ID": "367",
        "Name": "Pistachio Green - Dark"
      },
      "Value": {
        "Argb": -10974627,
        "Hex": "588A5D"
      }
    },
    {
      "Key": {
        "PaletteType": "DMC",
        "ID": "368",
        "Name": "Pistachio Green - Light"
      },
      "Value": {
        "Argb": -6766197,
        "Hex": "98C18B"
      }
    },
    {
      "Key": {
        "PaletteType": "DMC",
        "ID": "369",
        "Name": "Pistachio Green - Very Light"
      },
      "Value": {
        "Argb": -3874124,
        "Hex": "C4E2B4"
      }
    },
    {
      "Key": {
        "PaletteType": "DMC",
        "ID": "370",
        "Name": "Mustard - Medium"
      },
      "Value": {
        "Argb": -6254508,
        "Hex": "A09054"
      }
    },
    {
      "Key": {
        "PaletteType": "DMC",
        "ID": "371",
        "Name": "Mustard"
      },
      "Value": {
        "Argb": -5925027,
        "Hex": "A5975D"
      }
    },
    {
      "Key": {
        "PaletteType": "DMC",
        "ID": "372",
        "Name": "Mustard - Light"
      },
      "Value": {
        "Argb": -5132680,
        "Hex": "B1AE78"
      }
    },
    {
      "Key": {
        "PaletteType": "DMC",
        "ID": "400",
        "Name": "Mahogany - Dark"
      },
      "Value": {
        "Argb": -7515616,
        "Hex": "8D5220"
      }
    },
    {
      "Key": {
        "PaletteType": "DMC",
        "ID": "402",
        "Name": "Mahogany - Very Light"
      },
      "Value": {
        "Argb": -1595030,
        "Hex": "E7A96A"
      }
    },
    {
      "Key": {
        "PaletteType": "DMC",
        "ID": "407",
        "Name": "Desert Sand - Dark"
      },
      "Value": {
        "Argb": -4352134,
        "Hex": "BD977A"
      }
    },
    {
      "Key": {
        "PaletteType": "DMC",
        "ID": "413",
        "Name": "Pewter Gray - Dark"
      },
      "Value": {
        "Argb": -10984611,
        "Hex": "58635D"
      }
    },
    {
      "Key": {
        "PaletteType": "DMC",
        "ID": "414",
        "Name": "Steel Gray - Dark"
      },
      "Value": {
        "Argb": -8419957,
        "Hex": "7F858B"
      }
    },
    {
      "Key": {
        "PaletteType": "DMC",
        "ID": "415",
        "Name": "Pearl Gray"
      },
      "Value": {
        "Argb": -4668987,
        "Hex": "B8C1C5"
      }
    },
    {
      "Key": {
        "PaletteType": "DMC",
        "ID": "420",
        "Name": "Hazelnut Brown - Dark"
      },
      "Value": {
        "Argb": -6521276,
        "Hex": "9C7E44"
      }
    },
    {
      "Key": {
        "PaletteType": "DMC",
        "ID": "422",
        "Name": "Hazelnut Brown - Light"
      },
      "Value": {
        "Argb": -3097991,
        "Hex": "D0BA79"
      }
    },
    {
      "Key": {
        "PaletteType": "DMC",
        "ID": "433",
        "Name": "Brown - Medium"
      },
      "Value": {
        "Argb": -9086931,
        "Hex": "75582D"
      }
    },
    {
      "Key": {
        "PaletteType": "DMC",
        "ID": "434",
        "Name": "Brown - Light"
      },
      "Value": {
        "Argb": -7181774,
        "Hex": "926A32"
      }
    },
    {
      "Key": {
        "PaletteType": "DMC",
        "ID": "435",
        "Name": "Brown - Very Light"
      },
      "Value": {
        "Argb": -4880569,
        "Hex": "B58747"
      }
    },
    {
      "Key": {
        "PaletteType": "DMC",
        "ID": "436",
        "Name": "Tan"
      },
      "Value": {
        "Argb": -3299992,
        "Hex": "CDA568"
      }
    },
    {
      "Key": {
        "PaletteType": "DMC",
        "ID": "437",
        "Name": "Tan - Light"
      },
      "Value": {
        "Argb": -2508679,
        "Hex": "D9B879"
      }
    },
    {
      "Key": {
        "PaletteType": "DMC",
        "ID": "444",
        "Name": "Lemon - Dark"
      },
      "Value": {
        "Argb": -666368,
        "Hex": "F5D500"
      }
    },
    {
      "Key": {
        "PaletteType": "DMC",
        "ID": "445",
        "Name": "Lemon - Light"
      },
      "Value": {
        "Argb": -987771,
        "Hex": "F0ED85"
      }
    },
    {
      "Key": {
        "PaletteType": "DMC",
        "ID": "451",
        "Name": "Shell Gray - Dark"
      },
      "Value": {
        "Argb": -6845567,
        "Hex": "978B81"
      }
    },
    {
      "Key": {
        "PaletteType": "DMC",
        "ID": "452",
        "Name": "Shell Gray - Medium"
      },
      "Value": {
        "Argb": -4477274,
        "Hex": "BBAEA6"
      }
    },
    {
      "Key": {
        "PaletteType": "DMC",
        "ID": "453",
        "Name": "Shell Gray - Light"
      },
      "Value": {
        "Argb": -3422277,
        "Hex": "CBC7BB"
      }
    },
    {
      "Key": {
        "PaletteType": "DMC",
        "ID": "469",
        "Name": "Avocado Green"
      },
      "Value": {
        "Argb": -10191561,
        "Hex": "647D37"
      }
    },
    {
      "Key": {
        "PaletteType": "DMC",
        "ID": "470",
        "Name": "Avocado Green - Light"
      },
      "Value": {
        "Argb": -7823296,
        "Hex": "88A040"
      }
    },
    {
      "Key": {
        "PaletteType": "DMC",
        "ID": "471",
        "Name": "Avocado Green - Very Light"
      },
      "Value": {
        "Argb": -6967720,
        "Hex": "95AE58"
      }
    },
    {
      "Key": {
        "PaletteType": "DMC",
        "ID": "472",
        "Name": "Avocado Green - Ultra Light"
      },
      "Value": {
        "Argb": -4075909,
        "Hex": "C1CE7B"
      }
    },
    {
      "Key": {
        "PaletteType": "DMC",
        "ID": "498",
        "Name": "Red - Dark"
      },
      "Value": {
        "Argb": -6736847,
        "Hex": "993431"
      }
    },
    {
      "Key": {
        "PaletteType": "DMC",
        "ID": "500",
        "Name": "Blue Green - Very Dark"
      },
      "Value": {
        "Argb": -13743045,
        "Hex": "2E4C3B"
      }
    },
    {
      "Key": {
        "PaletteType": "DMC",
        "ID": "501",
        "Name": "Blue Green - Dark"
      },
      "Value": {
        "Argb": -11896734,
        "Hex": "4A7862"
      }
    },
    {
      "Key": {
        "PaletteType": "DMC",
        "ID": "502",
        "Name": "Blue Green"
      },
      "Value": {
        "Argb": -9922434,
        "Hex": "68987E"
      }
    },
    {
      "Key": {
        "PaletteType": "DMC",
        "ID": "503",
        "Name": "Blue Green - Medium"
      },
      "Value": {
        "Argb": -8212070,
        "Hex": "82B19A"
      }
    },
    {
      "Key": {
        "PaletteType": "DMC",
        "ID": "505",
        "Name": "Grass Green - Dark"
      },
      "Value": {
        "Argb": -12484013,
        "Hex": "418253"
      }
    },
    {
      "Key": {
        "PaletteType": "DMC",
        "ID": "517",
        "Name": "Wedgewood - Dark"
      },
      "Value": {
        "Argb": -12355420,
        "Hex": "4378A4"
      }
    },
    {
      "Key": {
        "PaletteType": "DMC",
        "ID": "518",
        "Name": "Wedgewood - Light"
      },
      "Value": {
        "Argb": -10182215,
        "Hex": "64A1B9"
      }
    },
    {
      "Key": {
        "PaletteType": "DMC",
        "ID": "519",
        "Name": "Sky Blue"
      },
      "Value": {
        "Argb": -7225129,
        "Hex": "91C0D7"
      }
    },
    {
      "Key": {
        "PaletteType": "DMC",
        "ID": "520",
        "Name": "Fern Green - Dark"
      },
      "Value": {
        "Argb": -11375286,
        "Hex": "526D4A"
      }
    },
    {
      "Key": {
        "PaletteType": "DMC",
        "ID": "522",
        "Name": "Fern Green"
      },
      "Value": {
        "Argb": -7429507,
        "Hex": "8EA27D"
      }
    },
    {
      "Key": {
        "PaletteType": "DMC",
        "ID": "523",
        "Name": "Fern Green - Light"
      },
      "Value": {
        "Argb": -6114419,
        "Hex": "A2B38D"
      }
    },
    {
      "Key": {
        "PaletteType": "DMC",
        "ID": "524",
        "Name": "Fern Green - Very Light"
      },
      "Value": {
        "Argb": -5393001,
        "Hex": "ADB597"
      }
    },
    {
      "Key": {
        "PaletteType": "DMC",
        "ID": "535",
        "Name": "Ash Gray - Very Light"
      },
      "Value": {
        "Argb": -10261669,
        "Hex": "636B5B"
      }
    },
    {
      "Key": {
        "PaletteType": "DMC",
        "ID": "543",
        "Name": "Beige Brown - Ultra Very Light"
      },
      "Value": {
        "Argb": -2042179,
        "Hex": "E0D6BD"
      }
    },
    {
      "Key": {
        "PaletteType": "DMC",
        "ID": "550",
        "Name": "Violet - Very Dark"
      },
      "Value": {
        "Argb": -11454121,
        "Hex": "513957"
      }
    },
    {
      "Key": {
        "PaletteType": "DMC",
        "ID": "552",
        "Name": "Violet - Medium"
      },
      "Value": {
        "Argb": -7840624,
        "Hex": "885C90"
      }
    },
    {
      "Key": {
        "PaletteType": "DMC",
        "ID": "553",
        "Name": "Violet"
      },
      "Value": {
        "Argb": -6129494,
        "Hex": "A278AA"
      }
    },
    {
      "Key": {
        "PaletteType": "DMC",
        "ID": "554",
        "Name": "Violet - Light"
      },
      "Value": {
        "Argb": -3233588,
        "Hex": "CEA8CC"
      }
    },
    {
      "Key": {
        "PaletteType": "DMC",
        "ID": "561",
        "Name": "Jade - Very Dark"
      },
      "Value": {
        "Argb": -13142697,
        "Hex": "377557"
      }
    },
    {
      "Key": {
        "PaletteType": "DMC",
        "ID": "562",
        "Name": "Jade - Medium"
      },
      "Value": {
        "Argb": -10904723,
        "Hex": "599B6D"
      }
    },
    {
      "Key": {
        "PaletteType": "DMC",
        "ID": "563",
        "Name": "Jade - Light"
      },
      "Value": {
        "Argb": -7879778,
        "Hex": "87C39E"
      }
    },
    {
      "Key": {
        "PaletteType": "DMC",
        "ID": "564",
        "Name": "Jade - Very Light"
      },
      "Value": {
        "Argb": -6500181,
        "Hex": "9CD0AB"
      }
    },
    {
      "Key": {
        "PaletteType": "DMC",
        "ID": "580",
        "Name": "Moss Green - Dark"
      },
      "Value": {
        "Argb": -9930963,
        "Hex": "68772D"
      }
    },
    {
      "Key": {
        "PaletteType": "DMC",
        "ID": "581",
        "Name": "Moss Green"
      },
      "Value": {
        "Argb": -8088016,
        "Hex": "849630"
      }
    },
    {
      "Key": {
        "PaletteType": "DMC",
        "ID": "597",
        "Name": "Turquoise"
      },
      "Value": {
        "Argb": -9392460,
        "Hex": "70AEB4"
      }
    },
    {
      "Key": {
        "PaletteType": "DMC",
        "ID": "598",
        "Name": "Turquoise - Light"
      },
      "Value": {
        "Argb": -6828854,
        "Hex": "97CCCA"
      }
    },
    {
      "Key": {
        "PaletteType": "DMC",
        "ID": "600",
        "Name": "Cranberry - Very Dark"
      },
      "Value": {
        "Argb": -4901034,
        "Hex": "B53756"
      }
    },
    {
      "Key": {
        "PaletteType": "DMC",
        "ID": "601",
        "Name": "Cranberry - Dark"
      },
      "Value": {
        "Argb": -3324820,
        "Hex": "CD446C"
      }
    },
    {
      "Key": {
        "PaletteType": "DMC",
        "ID": "602",
        "Name": "Cranberry - Medium"
      },
      "Value": {
        "Argb": -2665602,
        "Hex": "D7537E"
      }
    },
    {
      "Key": {
        "PaletteType": "DMC",
        "ID": "603",
        "Name": "Cranberry - Light Medium"
      },
      "Value": {
        "Argb": -1343321,
        "Hex": "EB80A7"
      }
    },
    {
      "Key": {
        "PaletteType": "DMC",
        "ID": "604",
        "Name": "Cranberry - Light"
      },
      "Value": {
        "Argb": -1271111,
        "Hex": "EC9AB9"
      }
    },
    {
      "Key": {
        "PaletteType": "DMC",
        "ID": "605",
        "Name": "Cranberry - Very Light"
      },
      "Value": {
        "Argb": -869677,
        "Hex": "F2BAD3"
      }
    },
    {
      "Key": {
        "PaletteType": "DMC",
        "ID": "606",
        "Name": "Orange-red - Bright"
      },
      "Value": {
        "Argb": -2151133,
        "Hex": "DF2D23"
      }
    },
    {
      "Key": {
        "PaletteType": "DMC",
        "ID": "608",
        "Name": "Orange - Bright"
      },
      "Value": {
        "Argb": -768460,
        "Hex": "F44634"
      }
    },
    {
      "Key": {
        "PaletteType": "DMC",
        "ID": "610",
        "Name": "Drab Brown - Dark"
      },
      "Value": {
        "Argb": -9213629,
        "Hex": "736943"
      }
    },
    {
      "Key": {
        "PaletteType": "DMC",
        "ID": "611",
        "Name": "Drab Brown"
      },
      "Value": {
        "Argb": -7765931,
        "Hex": "898055"
      }
    },
    {
      "Key": {
        "PaletteType": "DMC",
        "ID": "612",
        "Name": "Drab Brown - Light"
      },
      "Value": {
        "Argb": -5398672,
        "Hex": "AD9F70"
      }
    },
    {
      "Key": {
        "PaletteType": "DMC",
        "ID": "613",
        "Name": "Drab Brown - Very Light"
      },
      "Value": {
        "Argb": -3684958,
        "Hex": "C7C5A2"
      }
    },
    {
      "Key": {
        "PaletteType": "DMC",
        "ID": "632",
        "Name": "Desert Sand - Ultra Very Dark"
      },
      "Value": {
        "Argb": -7708091,
        "Hex": "8A6245"
      }
    },
    {
      "Key": {
        "PaletteType": "DMC",
        "ID": "640",
        "Name": "Beige Gray - Very Dark"
      },
      "Value": {
        "Argb": -7172759,
        "Hex": "928D69"
      }
    },
    {
      "Key": {
        "PaletteType": "DMC",
        "ID": "642",
        "Name": "Beige Gray - Dark"
      },
      "Value": {
        "Argb": -5921919,
        "Hex": "A5A381"
      }
    },
    {
      "Key": {
        "PaletteType": "DMC",
        "ID": "644",
        "Name": "Beige Gray - Medium"
      },
      "Value": {
        "Argb": -3421268,
        "Hex": "CBCBAC"
      }
    },
    {
      "Key": {
        "PaletteType": "DMC",
        "ID": "645",
        "Name": "Beaver Gray - Very Dark"
      },
      "Value": {
        "Argb": -9142683,
        "Hex": "747E65"
      }
    },
    {
      "Key": {
        "PaletteType": "DMC",
        "ID": "646",
        "Name": "Beaver Gray - Dark"
      },
      "Value": {
        "Argb": -7893383,
        "Hex": "878E79"
      }
    },
    {
      "Key": {
        "PaletteType": "DMC",
        "ID": "647",
        "Name": "Beaver Gray - Medium"
      },
      "Value": {
        "Argb": -6182769,
        "Hex": "A1A88F"
      }
    },
    {
      "Key": {
        "PaletteType": "DMC",
        "ID": "648",
        "Name": "Beaver Gray - Light"
      },
      "Value": {
        "Argb": -4538451,
        "Hex": "BABFAD"
      }
    },
    {
      "Key": {
        "PaletteType": "DMC",
        "ID": "666",
        "Name": "Red - Bright"
      },
      "Value": {
        "Argb": -3070425,
        "Hex": "D12627"
      }
    },
    {
      "Key": {
        "PaletteType": "DMC",
        "ID": "676",
        "Name": "Old Gold - Light"
      },
      "Value": {
        "Argb": -1914245,
        "Hex": "E2CA7B"
      }
    },
    {
      "Key": {
        "PaletteType": "DMC",
        "ID": "677",
        "Name": "Old Gold - Very Light"
      },
      "Value": {
        "Argb": -2041439,
        "Hex": "E0D9A1"
      }
    },
    {
      "Key": {
        "PaletteType": "DMC",
        "ID": "680",
        "Name": "Old Gold - Dark"
      },
      "Value": {
        "Argb": -5403071,
        "Hex": "AD8E41"
      }
    },
    {
      "Key": {
        "PaletteType": "DMC",
        "ID": "699",
        "Name": "Green"
      },
      "Value": {
        "Argb": -15701187,
        "Hex": "106B3D"
      }
    },
    {
      "Key": {
        "PaletteType": "DMC",
        "ID": "700",
        "Name": "Green - Bright"
      },
      "Value": {
        "Argb": -13729208,
        "Hex": "2E8248"
      }
    },
    {
      "Key": {
        "PaletteType": "DMC",
        "ID": "701",
        "Name": "Green - Light"
      },
      "Value": {
        "Argb": -12743605,
        "Hex": "3D8C4B"
      }
    },
    {
      "Key": {
        "PaletteType": "DMC",
        "ID": "702",
        "Name": "Kelly Green"
      },
      "Value": {
        "Argb": -10903470,
        "Hex": "59A052"
      }
    },
    {
      "Key": {
        "PaletteType": "DMC",
        "ID": "703",
        "Name": "Chartreuse"
      },
      "Value": {
        "Argb": -8275874,
        "Hex": "81B85E"
      }
    },
    {
      "Key": {
        "PaletteType": "DMC",
        "ID": "704",
        "Name": "Chartreuse - Bright"
      },
      "Value": {
        "Argb": -7094953,
        "Hex": "93BD57"
      }
    },
    {
      "Key": {
        "PaletteType": "DMC",
        "ID": "712",
        "Name": "Cream"
      },
      "Value": {
        "Argb": -1513000,
        "Hex": "E8E9D8"
      }
    },
    {
      "Key": {
        "PaletteType": "DMC",
        "ID": "718",
        "Name": "Plum"
      },
      "Value": {
        "Argb": -5684366,
        "Hex": "A94372"
      }
    },
    {
      "Key": {
        "PaletteType": "DMC",
        "ID": "720",
        "Name": "Orange Spice - Dark"
      },
      "Value": {
        "Argb": -2465242,
        "Hex": "DA6226"
      }
    },
    {
      "Key": {
        "PaletteType": "DMC",
        "ID": "721",
        "Name": "Orange Spice - Medium"
      },
      "Value": {
        "Argb": -1081536,
        "Hex": "EF7F40"
      }
    },
    {
      "Key": {
        "PaletteType": "DMC",
        "ID": "722",
        "Name": "Orange Spice - Light"
      },
      "Value": {
        "Argb": -612506,
        "Hex": "F6A766"
      }
    },
    {
      "Key": {
        "PaletteType": "DMC",
        "ID": "725",
        "Name": "Topaz"
      },
      "Value": {
        "Argb": -732594,
        "Hex": "F4D24E"
      }
    },
    {
      "Key": {
        "PaletteType": "DMC",
        "ID": "726",
        "Name": "Topaz - Light"
      },
      "Value": {
        "Argb": -662701,
        "Hex": "F5E353"
      }
    },
    {
      "Key": {
        "PaletteType": "DMC",
        "ID": "727",
        "Name": "Topaz - Very Light"
      },
      "Value": {
        "Argb": -923004,
        "Hex": "F1EA84"
      }
    },
    {
      "Key": {
        "PaletteType": "DMC",
        "ID": "728",
        "Name": "Golden Yellow"
      },
      "Value": {
        "Argb": -1261764,
        "Hex": "ECBF3C"
      }
    },
    {
      "Key": {
        "PaletteType": "DMC",
        "ID": "729",
        "Name": "Old Gold - Medium"
      },
      "Value": {
        "Argb": -3363752,
        "Hex": "CCAC58"
      }
    },
    {
      "Key": {
        "PaletteType": "DMC",
        "ID": "730",
        "Name": "Olive Green - Very Dark"
      },
      "Value": {
        "Argb": -9211861,
        "Hex": "73702B"
      }
    },
    {
      "Key": {
        "PaletteType": "DMC",
        "ID": "732",
        "Name": "Olive Green"
      },
      "Value": {
        "Argb": -8094166,
        "Hex": "847E2A"
      }
    },
    {
      "Key": {
        "PaletteType": "DMC",
        "ID": "733",
        "Name": "Olive Green - Medium"
      },
      "Value": {
        "Argb": -5463490,
        "Hex": "ACA23E"
      }
    },
    {
      "Key": {
        "PaletteType": "DMC",
        "ID": "734",
        "Name": "Olive Green - Light"
      },
      "Value": {
        "Argb": -4410533,
        "Hex": "BCB35B"
      }
    },
    {
      "Key": {
        "PaletteType": "DMC",
        "ID": "738",
        "Name": "Tan - Very Light"
      },
      "Value": {
        "Argb": -2505841,
        "Hex": "D9C38F"
      }
    },
    {
      "Key": {
        "PaletteType": "DMC",
        "ID": "739",
        "Name": "Tan - Ultra Very Light"
      },
      "Value": {
        "Argb": -1713486,
        "Hex": "E5DAB2"
      }
    },
    {
      "Key": {
        "PaletteType": "DMC",
        "ID": "740",
        "Name": "Tangerine"
      },
      "Value": {
        "Argb": -691175,
        "Hex": "F57419"
      }
    },
    {
      "Key": {
        "PaletteType": "DMC",
        "ID": "741",
        "Name": "Tangerine - Medium"
      },
      "Value": {
        "Argb": -616666,
        "Hex": "F69726"
      }
    },
    {
      "Key": {
        "PaletteType": "DMC",
        "ID": "742",
        "Name": "Tangerine - Light"
      },
      "Value": {
        "Argb": -475607,
        "Hex": "F8BE29"
      }
    },
    {
      "Key": {
        "PaletteType": "DMC",
        "ID": "743",
        "Name": "Yellow - Medium"
      },
      "Value": {
        "Argb": -599977,
        "Hex": "F6D857"
      }
    },
    {
      "Key": {
        "PaletteType": "DMC",
        "ID": "744",
        "Name": "Yellow - Pale"
      },
      "Value": {
        "Argb": -858751,
        "Hex": "F2E581"
      }
    },
    {
      "Key": {
        "PaletteType": "DMC",
        "ID": "745",
        "Name": "Yellow - Light Pale"
      },
      "Value": {
        "Argb": -1054046,
        "Hex": "EFEAA2"
      }
    },
    {
      "Key": {
        "PaletteType": "DMC",
        "ID": "746",
        "Name": "Off White"
      },
      "Value": {
        "Argb": -1446964,
        "Hex": "E9EBCC"
      }
    },
    {
      "Key": {
        "PaletteType": "DMC",
        "ID": "747",
        "Name": "Sky Blue - Very Light"
      },
      "Value": {
        "Argb": -3675928,
        "Hex": "C7E8E8"
      }
    },
    {
      "Key": {
        "PaletteType": "DMC",
        "ID": "754",
        "Name": "Peach - Light"
      },
      "Value": {
        "Argb": -1126993,
        "Hex": "EECDAF"
      }
    },
    {
      "Key": {
        "PaletteType": "DMC",
        "ID": "758",
        "Name": "Terra Cotta - Very Light"
      },
      "Value": {
        "Argb": -1789037,
        "Hex": "E4B393"
      }
    },
    {
      "Key": {
        "PaletteType": "DMC",
        "ID": "760",
        "Name": "Salmon"
      },
      "Value": {
        "Argb": -1139051,
        "Hex": "EE9E95"
      }
    },
    {
      "Key": {
        "PaletteType": "DMC",
        "ID": "761",
        "Name": "Salmon - Light"
      },
      "Value": {
        "Argb": -868424,
        "Hex": "F2BFB8"
      }
    },
    {
      "Key": {
        "PaletteType": "DMC",
        "ID": "762",
        "Name": "Pearl Gray - Very Light"
      },
      "Value": {
        "Argb": -2498591,
        "Hex": "D9DFE1"
      }
    },
    {
      "Key": {
        "PaletteType": "DMC",
        "ID": "772",
        "Name": "Yellow Green - Very Light"
      },
      "Value": {
        "Argb": -3087185,
        "Hex": "D0E4AF"
      }
    },
    {
      "Key": {
        "PaletteType": "DMC",
        "ID": "775",
        "Name": "Baby Blue - Very Light"
      },
      "Value": {
        "Argb": -3218200,
        "Hex": "CEE4E8"
      }
    },
    {
      "Key": {
        "PaletteType": "DMC",
        "ID": "777",
        "Name": "Red - Deep"
      },
      "Value": {
        "Argb": -7719109,
        "Hex": "8A373B"
      }
    },
    {
      "Key": {
        "PaletteType": "DMC",
        "ID": "778",
        "Name": "Antique Mauve - Very Light"
      },
      "Value": {
        "Argb": -2443338,
        "Hex": "DAB7B6"
      }
    },
    {
      "Key": {
        "PaletteType": "DMC",
        "ID": "779",
        "Name": "Brown"
      },
      "Value": {
        "Argb": -9611448,
        "Hex": "6D5748"
      }
    },
    {
      "Key": {
        "PaletteType": "DMC",
        "ID": "780",
        "Name": "Topaz - Ultra Very Dark"
      },
      "Value": {
        "Argb": -6854612,
        "Hex": "97682C"
      }
    },
    {
      "Key": {
        "PaletteType": "DMC",
        "ID": "782",
        "Name": "Topaz - Dark"
      },
      "Value": {
        "Argb": -4947157,
        "Hex": "B4832B"
      }
    },
    {
      "Key": {
        "PaletteType": "DMC",
        "ID": "783",
        "Name": "Topaz - Medium"
      },
      "Value": {
        "Argb": -3236297,
        "Hex": "CE9E37"
      }
    },
    {
      "Key": {
        "PaletteType": "DMC",
        "ID": "791",
        "Name": "Cornflower Blue - Very Dark"
      },
      "Value": {
        "Argb": -12433543,
        "Hex": "424779"
      }
    },
    {
      "Key": {
        "PaletteType": "DMC",
        "ID": "792",
        "Name": "Cornflower Blue - Dark"
      },
      "Value": {
        "Argb": -10984034,
        "Hex": "58659E"
      }
    },
    {
      "Key": {
        "PaletteType": "DMC",
        "ID": "793",
        "Name": "Cornflower Blue - Medium"
      },
      "Value": {
        "Argb": -8941898,
        "Hex": "778EB6"
      }
    },
    {
      "Key": {
        "PaletteType": "DMC",
        "ID": "794",
        "Name": "Cornflower Blue - Light"
      },
      "Value": {
        "Argb": -7163955,
        "Hex": "92AFCD"
      }
    },
    {
      "Key": {
        "PaletteType": "DMC",
        "ID": "796",
        "Name": "Royal Blue - Dark"
      },
      "Value": {
        "Argb": -13614465,
        "Hex": "30427F"
      }
    },
    {
      "Key": {
        "PaletteType": "DMC",
        "ID": "797",
        "Name": "Royal Blue"
      },
      "Value": {
        "Argb": -12494956,
        "Hex": "415794"
      }
    },
    {
      "Key": {
        "PaletteType": "DMC",
        "ID": "798",
        "Name": "Delft Blue - Dark"
      },
      "Value": {
        "Argb": -11767373,
        "Hex": "4C71B3"
      }
    },
    {
      "Key": {
        "PaletteType": "DMC",
        "ID": "799",
        "Name": "Delft Blue - Medium"
      },
      "Value": {
        "Argb": -8806710,
        "Hex": "799ECA"
      }
    },
    {
      "Key": {
        "PaletteType": "DMC",
        "ID": "800",
        "Name": "Delft Blue - Pale"
      },
      "Value": {
        "Argb": -5320732,
        "Hex": "AECFE4"
      }
    },
    {
      "Key": {
        "PaletteType": "DMC",
        "ID": "801",
        "Name": "Coffee Brown - Dark"
      },
      "Value": {
        "Argb": -9678033,
        "Hex": "6C532F"
      }
    },
    {
      "Key": {
        "PaletteType": "DMC",
        "ID": "803",
        "Name": "Blue - Deep"
      },
      "Value": {
        "Argb": -13874833,
        "Hex": "2C496F"
      }
    },
    {
      "Key": {
        "PaletteType": "DMC",
        "ID": "807",
        "Name": "Peacock Blue"
      },
      "Value": {
        "Argb": -10443338,
        "Hex": "60A5B6"
      }
    },
    {
      "Key": {
        "PaletteType": "DMC",
        "ID": "809",
        "Name": "Delft Blue"
      },
      "Value": {
        "Argb": -7228965,
        "Hex": "91B1DB"
      }
    },
    {
      "Key": {
        "PaletteType": "DMC",
        "ID": "813",
        "Name": "Blue - Light"
      },
      "Value": {
        "Argb": -8146739,
        "Hex": "83B0CD"
      }
    },
    {
      "Key": {
        "PaletteType": "DMC",
        "ID": "814",
        "Name": "Garnet - Dark"
      },
      "Value": {
        "Argb": -9357005,
        "Hex": "713933"
      }
    },
    {
      "Key": {
        "PaletteType": "DMC",
        "ID": "815",
        "Name": "Garnet - Medium"
      },
      "Value": {
        "Argb": -7980750,
        "Hex": "863932"
      }
    },
    {
      "Key": {
        "PaletteType": "DMC",
        "ID": "816",
        "Name": "Garnet"
      },
      "Value": {
        "Argb": -6865349,
        "Hex": "973E3B"
      }
    },
    {
      "Key": {
        "PaletteType": "DMC",
        "ID": "817",
        "Name": "Coral Red - Very Dark"
      },
      "Value": {
        "Argb": -5231837,
        "Hex": "B02B23"
      }
    },
    {
      "Key": {
        "PaletteType": "DMC",
        "ID": "818",
        "Name": "Baby Pink"
      },
      "Value": {
        "Argb": -1058604,
        "Hex": "EFD8D4"
      }
    },
    {
      "Key": {
        "PaletteType": "DMC",
        "ID": "819",
        "Name": "Baby Pink - Light"
      },
      "Value": {
        "Argb": -1187108,
        "Hex": "EDE2DC"
      }
    },
    {
      "Key": {
        "PaletteType": "DMC",
        "ID": "820",
        "Name": "Royal Blue - Very Dark"
      },
      "Value": {
        "Argb": -14141067,
        "Hex": "283975"
      }
    },
    {
      "Key": {
        "PaletteType": "DMC",
        "ID": "822",
        "Name": "Beige Gray - Light"
      },
      "Value": {
        "Argb": -1842488,
        "Hex": "E3E2C8"
      }
    },
    {
      "Key": {
        "PaletteType": "DMC",
        "ID": "823",
        "Name": "Blue - Dark"
      },
      "Value": {
        "Argb": -13682614,
        "Hex": "2F384A"
      }
    },
    {
      "Key": {
        "PaletteType": "DMC",
        "ID": "824",
        "Name": "Blue - Very Dark"
      },
      "Value": {
        "Argb": -12885358,
        "Hex": "3B6292"
      }
    },
    {
      "Key": {
        "PaletteType": "DMC",
        "ID": "825",
        "Name": "Blue - Dark"
      },
      "Value": {
        "Argb": -12554079,
        "Hex": "4070A1"
      }
    },
    {
      "Key": {
        "PaletteType": "DMC",
        "ID": "826",
        "Name": "Blue - Medium"
      },
      "Value": {
        "Argb": -10579524,
        "Hex": "5E91BC"
      }
    },
    {
      "Key": {
        "PaletteType": "DMC",
        "ID": "827",
        "Name": "Blue - Very Light"
      },
      "Value": {
        "Argb": -5385755,
        "Hex": "ADD1E5"
      }
    },
    {
      "Key": {
        "PaletteType": "DMC",
        "ID": "828",
        "Name": "Blue - Ultra Very Light"
      },
      "Value": {
        "Argb": -4136990,
        "Hex": "C0DFE2"
      }
    },
    {
      "Key": {
        "PaletteType": "DMC",
        "ID": "829",
        "Name": "Golden Olive - Very Dark"
      },
      "Value": {
        "Argb": -9413076,
        "Hex": "705E2C"
      }
    },
    {
      "Key": {
        "PaletteType": "DMC",
        "ID": "830",
        "Name": "Golden Olive - Dark"
      },
      "Value": {
        "Argb": -8622030,
        "Hex": "7C7032"
      }
    },
    {
      "Key": {
        "PaletteType": "DMC",
        "ID": "831",
        "Name": "Golden Olive - Medium"
      },
      "Value": {
        "Argb": -7570127,
        "Hex": "8C7D31"
      }
    },
    {
      "Key": {
        "PaletteType": "DMC",
        "ID": "832",
        "Name": "Golden Olive"
      },
      "Value": {
        "Argb": -5597894,
        "Hex": "AA953A"
      }
    },
    {
      "Key": {
        "PaletteType": "DMC",
        "ID": "833",
        "Name": "Golden Olive - Light"
      },
      "Value": {
        "Argb": -4478640,
        "Hex": "BBA950"
      }
    },
    {
      "Key": {
        "PaletteType": "DMC",
        "ID": "834",
        "Name": "Golden Olive - Very Light"
      },
      "Value": {
        "Argb": -3293593,
        "Hex": "CDBE67"
      }
    },
    {
      "Key": {
        "PaletteType": "DMC",
        "ID": "838",
        "Name": "Beige Brown - Very Dark"
      },
      "Value": {
        "Argb": -10662603,
        "Hex": "5D4D35"
      }
    },
    {
      "Key": {
        "PaletteType": "DMC",
        "ID": "839",
        "Name": "Beige Brown - Dark"
      },
      "Value": {
        "Argb": -9478589,
        "Hex": "6F5E43"
      }
    },
    {
      "Key": {
        "PaletteType": "DMC",
        "ID": "840",
        "Name": "Beige Brown - Medium"
      },
      "Value": {
        "Argb": -7109792,
        "Hex": "938360"
      }
    },
    {
      "Key": {
        "PaletteType": "DMC",
        "ID": "841",
        "Name": "Beige Brown - Light"
      },
      "Value": {
        "Argb": -5530499,
        "Hex": "AB9C7D"
      }
    },
    {
      "Key": {
        "PaletteType": "DMC",
        "ID": "842",
        "Name": "Beige Brown - Very Light"
      },
      "Value": {
        "Argb": -3094869,
        "Hex": "D0C6AB"
      }
    },
    {
      "Key": {
        "PaletteType": "DMC",
        "ID": "844",
        "Name": "Beaver Gray - Ultra Dark"
      },
      "Value": {
        "Argb": -10591407,
        "Hex": "5E6351"
      }
    },
    {
      "Key": {
        "PaletteType": "DMC",
        "ID": "869",
        "Name": "Hazelnut Brown - Very Dark"
      },
      "Value": {
        "Argb": -8295625,
        "Hex": "816B37"
      }
    },
    {
      "Key": {
        "PaletteType": "DMC",
        "ID": "890",
        "Name": "Pistachio Green - Ultra Dark"
      },
      "Value": {
        "Argb": -14200273,
        "Hex": "27522F"
      }
    },
    {
      "Key": {
        "PaletteType": "DMC",
        "ID": "891",
        "Name": "Carnation - Dark"
      },
      "Value": {
        "Argb": -1751717,
        "Hex": "E5455B"
      }
    },
    {
      "Key": {
        "PaletteType": "DMC",
        "ID": "892",
        "Name": "Carnation - Medium"
      },
      "Value": {
        "Argb": -1023889,
        "Hex": "F0606F"
      }
    },
    {
      "Key": {
        "PaletteType": "DMC",
        "ID": "893",
        "Name": "Carnation - Light"
      },
      "Value": {
        "Argb": -953722,
        "Hex": "F17286"
      }
    },
    {
      "Key": {
        "PaletteType": "DMC",
        "ID": "894",
        "Name": "Carnation - Very Light"
      },
      "Value": {
        "Argb": -748377,
        "Hex": "F494A7"
      }
    },
    {
      "Key": {
        "PaletteType": "DMC",
        "ID": "895",
        "Name": "Hunter Green - Very Dark"
      },
      "Value": {
        "Argb": -12819910,
        "Hex": "3C623A"
      }
    },
    {
      "Key": {
        "PaletteType": "DMC",
        "ID": "898",
        "Name": "Coffee Brown - Very Dark"
      },
      "Value": {
        "Argb": -10268369,
        "Hex": "63512F"
      }
    },
    {
      "Key": {
        "PaletteType": "DMC",
        "ID": "899",
        "Name": "Rose - Medium"
      },
      "Value": {
        "Argb": -1670764,
        "Hex": "E68194"
      }
    },
    {
      "Key": {
        "PaletteType": "DMC",
        "ID": "900",
        "Name": "Burnt Orange - Dark"
      },
      "Value": {
        "Argb": -3455951,
        "Hex": "CB4431"
      }
    },
    {
      "Key": {
        "PaletteType": "DMC",
        "ID": "902",
        "Name": "Garnet - Very Dark"
      },
      "Value": {
        "Argb": -9749709,
        "Hex": "6B3B33"
      }
    },
    {
      "Key": {
        "PaletteType": "DMC",
        "ID": "904",
        "Name": "Parrot Green - Very Dark"
      },
      "Value": {
        "Argb": -11963339,
        "Hex": "497435"
      }
    },
    {
      "Key": {
        "PaletteType": "DMC",
        "ID": "905",
        "Name": "Parrot Green - Dark"
      },
      "Value": {
        "Argb": -10975441,
        "Hex": "58872F"
      }
    },
    {
      "Key": {
        "PaletteType": "DMC",
        "ID": "906",
        "Name": "Parrot Green - Medium"
      },
      "Value": {
        "Argb": -9721568,
        "Hex": "6BA920"
      }
    },
    {
      "Key": {
        "PaletteType": "DMC",
        "ID": "907",
        "Name": "Parrot Green - Light"
      },
      "Value": {
        "Argb": -6767056,
        "Hex": "98BE30"
      }
    },
    {
      "Key": {
        "PaletteType": "DMC",
        "ID": "909",
        "Name": "Emerald Green - Very Dark"
      },
      "Value": {
        "Argb": -15239609,
        "Hex": "177647"
      }
    },
    {
      "Key": {
        "PaletteType": "DMC",
        "ID": "910",
        "Name": "Emerald Green - Dark"
      },
      "Value": {
        "Argb": -14579887,
        "Hex": "218751"
      }
    },
    {
      "Key": {
        "PaletteType": "DMC",
        "ID": "911",
        "Name": "Emerald Green - Medium"
      },
      "Value": {
        "Argb": -12673434,
        "Hex": "3E9E66"
      }
    },
    {
      "Key": {
        "PaletteType": "DMC",
        "ID": "912",
        "Name": "Emerald Green - Light"
      },
      "Value": {
        "Argb": -10504316,
        "Hex": "5FB784"
      }
    },
    {
      "Key": {
        "PaletteType": "DMC",
        "ID": "913",
        "Name": "Nile Green - Medium"
      },
      "Value": {
        "Argb": -8665454,
        "Hex": "7BC692"
      }
    },
    {
      "Key": {
        "PaletteType": "DMC",
        "ID": "915",
        "Name": "Plum - Dark"
      },
      "Value": {
        "Argb": -8506295,
        "Hex": "7E3449"
      }
    },
    {
      "Key": {
        "PaletteType": "DMC",
        "ID": "917",
        "Name": "Plum - Medium"
      },
      "Value": {
        "Argb": -6601366,
        "Hex": "9B456A"
      }
    },
    {
      "Key": {
        "PaletteType": "DMC",
        "ID": "918",
        "Name": "Red Copper - Dark"
      },
      "Value": {
        "Argb": -7254739,
        "Hex": "914D2D"
      }
    },
    {
      "Key": {
        "PaletteType": "DMC",
        "ID": "919",
        "Name": "Red Copper"
      },
      "Value": {
        "Argb": -5943512,
        "Hex": "A54F28"
      }
    },
    {
      "Key": {
        "PaletteType": "DMC",
        "ID": "920",
        "Name": "Copper - Medium"
      },
      "Value": {
        "Argb": -5285587,
        "Hex": "AF592D"
      }
    },
    {
      "Key": {
        "PaletteType": "DMC",
        "ID": "921",
        "Name": "Copper"
      },
      "Value": {
        "Argb": -3641288,
        "Hex": "C87038"
      }
    },
    {
      "Key": {
        "PaletteType": "DMC",
        "ID": "922",
        "Name": "Copper - Light"
      },
      "Value": {
        "Argb": -2062519,
        "Hex": "E08749"
      }
    },
    {
      "Key": {
        "PaletteType": "DMC",
        "ID": "924",
        "Name": "Gray Green - Very Dark"
      },
      "Value": {
        "Argb": -12427172,
        "Hex": "42605C"
      }
    },
    {
      "Key": {
        "PaletteType": "DMC",
        "ID": "926",
        "Name": "Gray Green - Medium"
      },
      "Value": {
        "Argb": -8349036,
        "Hex": "809A94"
      }
    },
    {
      "Key": {
        "PaletteType": "DMC",
        "ID": "927",
        "Name": "Gray Green - Light"
      },
      "Value": {
        "Argb": -5849676,
        "Hex": "A6BDB4"
      }
    },
    {
      "Key": {
        "PaletteType": "DMC",
        "ID": "928",
        "Name": "Gray Green - Very Light"
      },
      "Value": {
        "Argb": -4206391,
        "Hex": "BFD0C9"
      }
    },
    {
      "Key": {
        "PaletteType": "DMC",
        "ID": "930",
        "Name": "Antique Blue - Dark"
      },
      "Value": {
        "Argb": -12362137,
        "Hex": "435E67"
      }
    },
    {
      "Key": {
        "PaletteType": "DMC",
        "ID": "931",
        "Name": "Antique Blue - Medium"
      },
      "Value": {
        "Argb": -9991785,
        "Hex": "678997"
      }
    },
    {
      "Key": {
        "PaletteType": "DMC",
        "ID": "932",
        "Name": "Antique Blue - Light"
      },
      "Value": {
        "Argb": -7360839,
        "Hex": "8FAEB9"
      }
    },
    {
      "Key": {
        "PaletteType": "DMC",
        "ID": "934",
        "Name": "Avocado Green - BLACK"
      },
      "Value": {
        "Argb": -12694991,
        "Hex": "3E4A31"
      }
    },
    {
      "Key": {
        "PaletteType": "DMC",
        "ID": "935",
        "Name": "Avocado Green - Dark"
      },
      "Value": {
        "Argb": -11969477,
        "Hex": "495C3B"
      }
    },
    {
      "Key": {
        "PaletteType": "DMC",
        "ID": "936",
        "Name": "Avocado Green - Very Dark"
      },
      "Value": {
        "Argb": -11115470,
        "Hex": "566432"
      }
    },
    {
      "Key": {
        "PaletteType": "DMC",
        "ID": "937",
        "Name": "Avocado Green - Medium"
      },
      "Value": {
        "Argb": -10653386,
        "Hex": "5D7136"
      }
    },
    {
      "Key": {
        "PaletteType": "DMC",
        "ID": "938",
        "Name": "Coffee Brown - Ultra Dark"
      },
      "Value": {
        "Argb": -11516885,
        "Hex": "50442B"
      }
    },
    {
      "Key": {
        "PaletteType": "DMC",
        "ID": "939",
        "Name": "Blue - Very Dark"
      },
      "Value": {
        "Argb": -14209740,
        "Hex": "272D34"
      }
    },
    {
      "Key": {
        "PaletteType": "DMC",
        "ID": "943",
        "Name": "Aquamarine - Medium"
      },
      "Value": {
        "Argb": -14968449,
        "Hex": "1B997F"
      }
    },
    {
      "Key": {
        "PaletteType": "DMC",
        "ID": "945",
        "Name": "Tawny"
      },
      "Value": {
        "Argb": -1126746,
        "Hex": "EECEA6"
      }
    },
    {
      "Key": {
        "PaletteType": "DMC",
        "ID": "946",
        "Name": "Burnt Orange - Medium"
      },
      "Value": {
        "Argb": -1750236,
        "Hex": "E54B24"
      }
    },
    {
      "Key": {
        "PaletteType": "DMC",
        "ID": "947",
        "Name": "Burnt Orange"
      },
      "Value": {
        "Argb": -1487317,
        "Hex": "E94E2B"
      }
    },
    {
      "Key": {
        "PaletteType": "DMC",
        "ID": "948",
        "Name": "Peach - Very Light"
      },
      "Value": {
        "Argb": -1187380,
        "Hex": "EDE1CC"
      }
    },
    {
      "Key": {
        "PaletteType": "DMC",
        "ID": "950",
        "Name": "Desert Sand - Light"
      },
      "Value": {
        "Argb": -1586257,
        "Hex": "E7CBAF"
      }
    },
    {
      "Key": {
        "PaletteType": "DMC",
        "ID": "951",
        "Name": "Tawny - Light"
      },
      "Value": {
        "Argb": -1188163,
        "Hex": "EDDEBD"
      }
    },
    {
      "Key": {
        "PaletteType": "DMC",
        "ID": "954",
        "Name": "Nile Green"
      },
      "Value": {
        "Argb": -7286370,
        "Hex": "90D19E"
      }
    },
    {
      "Key": {
        "PaletteType": "DMC",
        "ID": "955",
        "Name": "Nile Green - Light"
      },
      "Value": {
        "Argb": -4462143,
        "Hex": "BBE9C1"
      }
    },
    {
      "Key": {
        "PaletteType": "DMC",
        "ID": "956",
        "Name": "Geranium"
      },
      "Value": {
        "Argb": -1153400,
        "Hex": "EE6688"
      }
    },
    {
      "Key": {
        "PaletteType": "DMC",
        "ID": "957",
        "Name": "Geranium - Pale"
      },
      "Value": {
        "Argb": -613707,
        "Hex": "F6A2B5"
      }
    },
    {
      "Key": {
        "PaletteType": "DMC",
        "ID": "958",
        "Name": "Seagreen - Dark"
      },
      "Value": {
        "Argb": -11750752,
        "Hex": "4CB2A0"
      }
    },
    {
      "Key": {
        "PaletteType": "DMC",
        "ID": "959",
        "Name": "Seagreen - Medium"
      },
      "Value": {
        "Argb": -9911886,
        "Hex": "68C1B2"
      }
    },
    {
      "Key": {
        "PaletteType": "DMC",
        "ID": "961",
        "Name": "Dusty Rose - Dark"
      },
      "Value": {
        "Argb": -2329467,
        "Hex": "DC7485"
      }
    },
    {
      "Key": {
        "PaletteType": "DMC",
        "ID": "962",
        "Name": "Dusty Rose - Medium"
      },
      "Value": {
        "Argb": -1799525,
        "Hex": "E48A9B"
      }
    },
    {
      "Key": {
        "PaletteType": "DMC",
        "ID": "963",
        "Name": "Dusty Rose - Ultra Very Light"
      },
      "Value": {
        "Argb": -930094,
        "Hex": "F1CED2"
      }
    },
    {
      "Key": {
        "PaletteType": "DMC",
        "ID": "964",
        "Name": "Seagreen - Light"
      },
      "Value": {
        "Argb": -6431275,
        "Hex": "9DDDD5"
      }
    },
    {
      "Key": {
        "PaletteType": "DMC",
        "ID": "966",
        "Name": "Baby Green - Medium"
      },
      "Value": {
        "Argb": -5779793,
        "Hex": "A7CEAF"
      }
    },
    {
      "Key": {
        "PaletteType": "DMC",
        "ID": "967",
        "Name": "Peach - Light"
      },
      "Value": {
        "Argb": -800586,
        "Hex": "F3C8B6"
      }
    },
    {
      "Key": {
        "PaletteType": "DMC",
        "ID": "970",
        "Name": "Pumpkin - Light"
      },
      "Value": {
        "Argb": -428491,
        "Hex": "F97635"
      }
    },
    {
      "Key": {
        "PaletteType": "DMC",
        "ID": "972",
        "Name": "Canary - Deep"
      },
      "Value": {
        "Argb": -804602,
        "Hex": "F3B906"
      }
    },
    {
      "Key": {
        "PaletteType": "DMC",
        "ID": "973",
        "Name": "Canary - Bright"
      },
      "Value": {
        "Argb": -666110,
        "Hex": "F5D602"
      }
    },
    {
      "Key": {
        "PaletteType": "DMC",
        "ID": "975",
        "Name": "Golden Brown - Dark"
      },
      "Value": {
        "Argb": -7644372,
        "Hex": "8B5B2C"
      }
    },
    {
      "Key": {
        "PaletteType": "DMC",
        "ID": "976",
        "Name": "Golden Brown - Medium"
      },
      "Value": {
        "Argb": -3897549,
        "Hex": "C48733"
      }
    },
    {
      "Key": {
        "PaletteType": "DMC",
        "ID": "977",
        "Name": "Golden Brown - Light"
      },
      "Value": {
        "Argb": -2185387,
        "Hex": "DEA755"
      }
    },
    {
      "Key": {
        "PaletteType": "DMC",
        "ID": "986",
        "Name": "Forest Green - Very Dark"
      },
      "Value": {
        "Argb": -12946373,
        "Hex": "3A743B"
      }
    },
    {
      "Key": {
        "PaletteType": "DMC",
        "ID": "987",
        "Name": "Forest Green - Dark"
      },
      "Value": {
        "Argb": -10580912,
        "Hex": "5E8C50"
      }
    },
    {
      "Key": {
        "PaletteType": "DMC",
        "ID": "988",
        "Name": "Forest Green - Medium"
      },
      "Value": {
        "Argb": -8935587,
        "Hex": "77A75D"
      }
    },
    {
      "Key": {
        "PaletteType": "DMC",
        "ID": "989",
        "Name": "Forest Green"
      },
      "Value": {
        "Argb": -7883666,
        "Hex": "87B46E"
      }
    },
    {
      "Key": {
        "PaletteType": "DMC",
        "ID": "991",
        "Name": "Aquamarine - Dark"
      },
      "Value": {
        "Argb": -14386587,
        "Hex": "247A65"
      }
    },
    {
      "Key": {
        "PaletteType": "DMC",
        "ID": "992",
        "Name": "Aquamarine - Light"
      },
      "Value": {
        "Argb": -11032174,
        "Hex": "57A992"
      }
    },
    {
      "Key": {
        "PaletteType": "DMC",
        "ID": "993",
        "Name": "Aquamarine - Very Light"
      },
      "Value": {
        "Argb": -8864089,
        "Hex": "78BEA7"
      }
    },
    {
      "Key": {
        "PaletteType": "DMC",
        "ID": "995",
        "Name": "Electric Blue - Dark"
      },
      "Value": {
        "Argb": -16683840,
        "Hex": "016CC0"
      }
    },
    {
      "Key": {
        "PaletteType": "DMC",
        "ID": "996",
        "Name": "Electric Blue - Medium"
      },
      "Value": {
        "Argb": -13785885,
        "Hex": "2DA4E3"
      }
    },
    {
      "Key": {
        "PaletteType": "DMC",
        "ID": "3011",
        "Name": "Khaki Green - Dark"
      },
      "Value": {
        "Argb": -9014209,
        "Hex": "76743F"
      }
    },
    {
      "Key": {
        "PaletteType": "DMC",
        "ID": "3012",
        "Name": "Khaki Green - Medium"
      },
      "Value": {
        "Argb": -6974893,
        "Hex": "959253"
      }
    },
    {
      "Key": {
        "PaletteType": "DMC",
        "ID": "3013",
        "Name": "Khaki Green - Light"
      },
      "Value": {
        "Argb": -5131653,
        "Hex": "B1B27B"
      }
    },
    {
      "Key": {
        "PaletteType": "DMC",
        "ID": "3021",
        "Name": "Brown Gray - Very Dark"
      },
      "Value": {
        "Argb": -10922179,
        "Hex": "59573D"
      }
    },
    {
      "Key": {
        "PaletteType": "DMC",
        "ID": "3022",
        "Name": "Brown Gray - Medium"
      },
      "Value": {
        "Argb": -6907010,
        "Hex": "969B7E"
      }
    },
    {
      "Key": {
        "PaletteType": "DMC",
        "ID": "3023",
        "Name": "Brown Gray - Light"
      },
      "Value": {
        "Argb": -5065062,
        "Hex": "B2B69A"
      }
    },
    {
      "Key": {
        "PaletteType": "DMC",
        "ID": "3024",
        "Name": "Brown Gray - Very Light"
      },
      "Value": {
        "Argb": -3420224,
        "Hex": "CBCFC0"
      }
    },
    {
      "Key": {
        "PaletteType": "DMC",
        "ID": "3031",
        "Name": "Mocha Brown - Very Dark"
      },
      "Value": {
        "Argb": -11384016,
        "Hex": "524B30"
      }
    },
    {
      "Key": {
        "PaletteType": "DMC",
        "ID": "3032",
        "Name": "Mocha Brown - Medium"
      },
      "Value": {
        "Argb": -5791623,
        "Hex": "A7A079"
      }
    },
    {
      "Key": {
        "PaletteType": "DMC",
        "ID": "3033",
        "Name": "Mocha Brown - Very Light"
      },
      "Value": {
        "Argb": -2303294,
        "Hex": "DCDAC2"
      }
    },
    {
      "Key": {
        "PaletteType": "DMC",
        "ID": "3041",
        "Name": "Antique Violet - Medium"
      },
      "Value": {
        "Argb": -7177856,
        "Hex": "927980"
      }
    },
    {
      "Key": {
        "PaletteType": "DMC",
        "ID": "3042",
        "Name": "Antique Violet - Light"
      },
      "Value": {
        "Argb": -4937808,
        "Hex": "B4A7B0"
      }
    },
    {
      "Key": {
        "PaletteType": "DMC",
        "ID": "3045",
        "Name": "Yellow Beige - Dark"
      },
      "Value": {
        "Argb": -4808091,
        "Hex": "B6A265"
      }
    },
    {
      "Key": {
        "PaletteType": "DMC",
        "ID": "3046",
        "Name": "Yellow Beige - Medium"
      },
      "Value": {
        "Argb": -3160961,
        "Hex": "CFC47F"
      }
    },
    {
      "Key": {
        "PaletteType": "DMC",
        "ID": "3047",
        "Name": "Yellow Beige - Light"
      },
      "Value": {
        "Argb": -2172508,
        "Hex": "DED9A4"
      }
    },
    {
      "Key": {
        "PaletteType": "DMC",
        "ID": "3051",
        "Name": "Green Gray - Dark"
      },
      "Value": {
        "Argb": -10327232,
        "Hex": "626B40"
      }
    },
    {
      "Key": {
        "PaletteType": "DMC",
        "ID": "3052",
        "Name": "Green Gray - Medium"
      },
      "Value": {
        "Argb": -7366035,
        "Hex": "8F9A6D"
      }
    },
    {
      "Key": {
        "PaletteType": "DMC",
        "ID": "3053",
        "Name": "Green Gray"
      },
      "Value": {
        "Argb": -6115968,
        "Hex": "A2AD80"
      }
    },
    {
      "Key": {
        "PaletteType": "DMC",
        "ID": "3064",
        "Name": "Desert Sand"
      },
      "Value": {
        "Argb": -3695754,
        "Hex": "C79B76"
      }
    },
    {
      "Key": {
        "PaletteType": "DMC",
        "ID": "3072",
        "Name": "Beaver Gray - Very Light"
      },
      "Value": {
        "Argb": -2761263,
        "Hex": "D5DDD1"
      }
    },
    {
      "Key": {
        "PaletteType": "DMC",
        "ID": "3078",
        "Name": "Golden Yellow - Very Light"
      },
      "Value": {
        "Argb": -1184599,
        "Hex": "EDECA9"
      }
    },
    {
      "Key": {
        "PaletteType": "DMC",
        "ID": "3325",
        "Name": "Baby Blue - Light"
      },
      "Value": {
        "Argb": -6044448,
        "Hex": "A3C4E0"
      }
    },
    {
      "Key": {
        "PaletteType": "DMC",
        "ID": "3326",
        "Name": "Rose - Light"
      },
      "Value": {
        "Argb": -1070160,
        "Hex": "EFABB0"
      }
    },
    {
      "Key": {
        "PaletteType": "DMC",
        "ID": "3328",
        "Name": "Salmon - Dark"
      },
      "Value": {
        "Argb": -2986910,
        "Hex": "D26C62"
      }
    },
    {
      "Key": {
        "PaletteType": "DMC",
        "ID": "3340",
        "Name": "Apricot - Medium"
      },
      "Value": {
        "Argb": -557477,
        "Hex": "F77E5B"
      }
    },
    {
      "Key": {
        "PaletteType": "DMC",
        "ID": "3341",
        "Name": "Apricot"
      },
      "Value": {
        "Argb": -546160,
        "Hex": "F7AA90"
      }
    },
    {
      "Key": {
        "PaletteType": "DMC",
        "ID": "3345",
        "Name": "Hunter Green - Dark"
      },
      "Value": {
        "Argb": -12030662,
        "Hex": "486D3A"
      }
    },
    {
      "Key": {
        "PaletteType": "DMC",
        "ID": "3346",
        "Name": "Hunter Green"
      },
      "Value": {
        "Argb": -9728435,
        "Hex": "6B8E4D"
      }
    },
    {
      "Key": {
        "PaletteType": "DMC",
        "ID": "3347",
        "Name": "Yellow Green - Medium"
      },
      "Value": {
        "Argb": -8412580,
        "Hex": "7FA25C"
      }
    },
    {
      "Key": {
        "PaletteType": "DMC",
        "ID": "3348",
        "Name": "Yellow Green - Light"
      },
      "Value": {
        "Argb": -4798593,
        "Hex": "B6C77F"
      }
    },
    {
      "Key": {
        "PaletteType": "DMC",
        "ID": "3350",
        "Name": "Dusty Rose - Ultra Dark"
      },
      "Value": {
        "Argb": -4631191,
        "Hex": "B95569"
      }
    },
    {
      "Key": {
        "PaletteType": "DMC",
        "ID": "3354",
        "Name": "Dusty Rose - Light"
      },
      "Value": {
        "Argb": -1858134,
        "Hex": "E3A5AA"
      }
    },
    {
      "Key": {
        "PaletteType": "DMC",
        "ID": "3362",
        "Name": "Pine Green - Dark"
      },
      "Value": {
        "Argb": -11113660,
        "Hex": "566B44"
      }
    },
    {
      "Key": {
        "PaletteType": "DMC",
        "ID": "3363",
        "Name": "Pine Green - Medium"
      },
      "Value": {
        "Argb": -9269920,
        "Hex": "728D60"
      }
    },
    {
      "Key": {
        "PaletteType": "DMC",
        "ID": "3364",
        "Name": "Pine Green"
      },
      "Value": {
        "Argb": -6903695,
        "Hex": "96A871"
      }
    },
    {
      "Key": {
        "PaletteType": "DMC",
        "ID": "3371",
        "Name": "Black Brown"
      },
      "Value": {
        "Argb": -12961498,
        "Hex": "3A3926"
      }
    },
    {
      "Key": {
        "PaletteType": "DMC",
        "ID": "3607",
        "Name": "Plum - Light"
      },
      "Value": {
        "Argb": -4234349,
        "Hex": "BF6393"
      }
    },
    {
      "Key": {
        "PaletteType": "DMC",
        "ID": "3608",
        "Name": "Plum - Very Light"
      },
      "Value": {
        "Argb": -2125123,
        "Hex": "DF92BD"
      }
    },
    {
      "Key": {
        "PaletteType": "DMC",
        "ID": "3609",
        "Name": "Plum - Ultra Light"
      },
      "Value": {
        "Argb": -1462317,
        "Hex": "E9AFD3"
      }
    },
    {
      "Key": {
        "PaletteType": "DMC",
        "ID": "3685",
        "Name": "Mauve - Very Dark"
      },
      "Value": {
        "Argb": -8635068,
        "Hex": "7C3D44"
      }
    },
    {
      "Key": {
        "PaletteType": "DMC",
        "ID": "3687",
        "Name": "Mauve"
      },
      "Value": {
        "Argb": -4627077,
        "Hex": "B9657B"
      }
    },
    {
      "Key": {
        "PaletteType": "DMC",
        "ID": "3688",
        "Name": "Mauve - Medium"
      },
      "Value": {
        "Argb": -2914149,
        "Hex": "D3889B"
      }
    },
    {
      "Key": {
        "PaletteType": "DMC",
        "ID": "3689",
        "Name": "Mauve - Light"
      },
      "Value": {
        "Argb": -1395000,
        "Hex": "EAB6C8"
      }
    },
    {
      "Key": {
        "PaletteType": "DMC",
        "ID": "3705",
        "Name": "Melon - Dark"
      },
      "Value": {
        "Argb": -1746082,
        "Hex": "E55B5E"
      }
    },
    {
      "Key": {
        "PaletteType": "DMC",
        "ID": "3706",
        "Name": "Melon - Medium"
      },
      "Value": {
        "Argb": -490610,
        "Hex": "F8838E"
      }
    },
    {
      "Key": {
        "PaletteType": "DMC",
        "ID": "3708",
        "Name": "Melon - Light"
      },
      "Value": {
        "Argb": -677962,
        "Hex": "F5A7B6"
      }
    },
    {
      "Key": {
        "PaletteType": "DMC",
        "ID": "3712",
        "Name": "Salmon - Medium"
      },
      "Value": {
        "Argb": -2129032,
        "Hex": "DF8378"
      }
    },
    {
      "Key": {
        "PaletteType": "DMC",
        "ID": "3713",
        "Name": "Salmon - Very Light"
      },
      "Value": {
        "Argb": -994869,
        "Hex": "F0D1CB"
      }
    },
    {
      "Key": {
        "PaletteType": "DMC",
        "ID": "3716",
        "Name": "Dusty Rose - Very Light"
      },
      "Value": {
        "Argb": -938310,
        "Hex": "F1AEBA"
      }
    },
    {
      "Key": {
        "PaletteType": "DMC",
        "ID": "3721",
        "Name": "Shell Pink - Dark"
      },
      "Value": {
        "Argb": -6334642,
        "Hex": "9F574E"
      }
    },
    {
      "Key": {
        "PaletteType": "DMC",
        "ID": "3722",
        "Name": "Shell Pink - Medium"
      },
      "Value": {
        "Argb": -5084057,
        "Hex": "B26C67"
      }
    },
    {
      "Key": {
        "PaletteType": "DMC",
        "ID": "3726",
        "Name": "Antique Mauve - Dark"
      },
      "Value": {
        "Argb": -6328979,
        "Hex": "9F6D6D"
      }
    },
    {
      "Key": {
        "PaletteType": "DMC",
        "ID": "3727",
        "Name": "Antique Mauve - Light"
      },
      "Value": {
        "Argb": -2774094,
        "Hex": "D5ABB2"
      }
    },
    {
      "Key": {
        "PaletteType": "DMC",
        "ID": "3731",
        "Name": "Dusty Rose - Very Dark"
      },
      "Value": {
        "Argb": -3511684,
        "Hex": "CA6A7C"
      }
    },
    {
      "Key": {
        "PaletteType": "DMC",
        "ID": "3733",
        "Name": "Dusty Rose"
      },
      "Value": {
        "Argb": -2257256,
        "Hex": "DD8E98"
      }
    },
    {
      "Key": {
        "PaletteType": "DMC",
        "ID": "3740",
        "Name": "Antique Violet - Dark"
      },
      "Value": {
        "Argb": -8625562,
        "Hex": "7C6266"
      }
    },
    {
      "Key": {
        "PaletteType": "DMC",
        "ID": "3743",
        "Name": "Antique Violet - Very Light"
      },
      "Value": {
        "Argb": -3488821,
        "Hex": "CAC3CB"
      }
    },
    {
      "Key": {
        "PaletteType": "DMC",
        "ID": "3746",
        "Name": "Blue Violet - Dark"
      },
      "Value": {
        "Argb": -8553543,
        "Hex": "7D7BB9"
      }
    },
    {
      "Key": {
        "PaletteType": "DMC",
        "ID": "3747",
        "Name": "Blue Violet - Very Light"
      },
      "Value": {
        "Argb": -3353113,
        "Hex": "CCD5E7"
      }
    },
    {
      "Key": {
        "PaletteType": "DMC",
        "ID": "3750",
        "Name": "Antique Blue - Very Dark"
      },
      "Value": {
        "Argb": -13677219,
        "Hex": "2F4D5D"
      }
    },
    {
      "Key": {
        "PaletteType": "DMC",
        "ID": "3752",
        "Name": "Antique Blue - Very Light"
      },
      "Value": {
        "Argb": -5453871,
        "Hex": "ACC7D1"
      }
    },
    {
      "Key": {
        "PaletteType": "DMC",
        "ID": "3753",
        "Name": "Antique Blue - Ultra Very Light"
      },
      "Value": {
        "Argb": -3876128,
        "Hex": "C4DAE0"
      }
    },
    {
      "Key": {
        "PaletteType": "DMC",
        "ID": "3755",
        "Name": "Baby Blue"
      },
      "Value": {
        "Argb": -7227690,
        "Hex": "91B6D6"
      }
    },
    {
      "Key": {
        "PaletteType": "DMC",
        "ID": "3756",
        "Name": "Baby Blue - Light"
      },
      "Value": {
        "Argb": -2233881,
        "Hex": "DDE9E7"
      }
    },
    {
      "Key": {
        "PaletteType": "DMC",
        "ID": "3760",
        "Name": "Wedgewood - Medium"
      },
      "Value": {
        "Argb": -11366994,
        "Hex": "528DAE"
      }
    },
    {
      "Key": {
        "PaletteType": "DMC",
        "ID": "3761",
        "Name": "Sky Blue - Light"
      },
      "Value": {
        "Argb": -5252636,
        "Hex": "AFD9E4"
      }
    },
    {
      "Key": {
        "PaletteType": "DMC",
        "ID": "3765",
        "Name": "Peacock Blue - Very Dark"
      },
      "Value": {
        "Argb": -13601646,
        "Hex": "307492"
      }
    },
    {
      "Key": {
        "PaletteType": "DMC",
        "ID": "3766",
        "Name": "Peacock Blue - Light"
      },
      "Value": {
        "Argb": -7748399,
        "Hex": "89C4D1"
      }
    },
    {
      "Key": {
        "PaletteType": "DMC",
        "ID": "3768",
        "Name": "Gray Green - Dark"
      },
      "Value": {
        "Argb": -10650245,
        "Hex": "5D7D7B"
      }
    },
    {
      "Key": {
        "PaletteType": "DMC",
        "ID": "3770",
        "Name": "Tawny - Very Light"
      },
      "Value": {
        "Argb": -1251117,
        "Hex": "ECE8D3"
      }
    },
    {
      "Key": {
        "PaletteType": "DMC",
        "ID": "3771",
        "Name": "Peach - Dark"
      },
      "Value": {
        "Argb": -1526385,
        "Hex": "E8B58F"
      }
    },
    {
      "Key": {
        "PaletteType": "DMC",
        "ID": "3772",
        "Name": "Desert Sand - Very Dark"
      },
      "Value": {
        "Argb": -5931681,
        "Hex": "A57D5F"
      }
    },
    {
      "Key": {
        "PaletteType": "DMC",
        "ID": "3774",
        "Name": "Desert Sand - Very Light"
      },
      "Value": {
        "Argb": -1649481,
        "Hex": "E6D4B7"
      }
    },
    {
      "Key": {
        "PaletteType": "DMC",
        "ID": "3776",
        "Name": "Mahogany - Light"
      },
      "Value": {
        "Argb": -3177656,
        "Hex": "CF8348"
      }
    },
    {
      "Key": {
        "PaletteType": "DMC",
        "ID": "3777",
        "Name": "Terra Cotta - Very Dark"
      },
      "Value": {
        "Argb": -7126476,
        "Hex": "934234"
      }
    },
    {
      "Key": {
        "PaletteType": "DMC",
        "ID": "3778",
        "Name": "Terra Cotta - Light"
      },
      "Value": {
        "Argb": -2714504,
        "Hex": "D69478"
      }
    },
    {
      "Key": {
        "PaletteType": "DMC",
        "ID": "3779",
        "Name": "Terra Cotta - Ultra Very Light"
      },
      "Value": {
        "Argb": -1326937,
        "Hex": "EBC0A7"
      }
    },
    {
      "Key": {
        "PaletteType": "DMC",
        "ID": "3781",
        "Name": "Mocha Brown - Dark"
      },
      "Value": {
        "Argb": -9740482,
        "Hex": "6B5F3E"
      }
    },
    {
      "Key": {
        "PaletteType": "DMC",
        "ID": "3782",
        "Name": "Mocha Brown - Light"
      },
      "Value": {
        "Argb": -4212845,
        "Hex": "BFB793"
      }
    },
    {
      "Key": {
        "PaletteType": "DMC",
        "ID": "3787",
        "Name": "Brown Gray - Dark"
      },
      "Value": {
        "Argb": -9342635,
        "Hex": "717155"
      }
    },
    {
      "Key": {
        "PaletteType": "DMC",
        "ID": "3790",
        "Name": "Beige Gray - Ultra Dark"
      },
      "Value": {
        "Argb": -7898534,
        "Hex": "877A5A"
      }
    },
    {
      "Key": {
        "PaletteType": "DMC",
        "ID": "3799",
        "Name": "Pewter Gray - Very Dark"
      },
      "Value": {
        "Argb": -11774902,
        "Hex": "4C544A"
      }
    },
    {
      "Key": {
        "PaletteType": "DMC",
        "ID": "3801",
        "Name": "Melon - Very Dark"
      },
      "Value": {
        "Argb": -1555378,
        "Hex": "E8444E"
      }
    },
    {
      "Key": {
        "PaletteType": "DMC",
        "ID": "3802",
        "Name": "Antique Mauve - Very Dark"
      },
      "Value": {
        "Argb": -8698805,
        "Hex": "7B444B"
      }
    },
    {
      "Key": {
        "PaletteType": "DMC",
        "ID": "3803",
        "Name": "Mauve - Dark"
      },
      "Value": {
        "Argb": -7190181,
        "Hex": "92495B"
      }
    },
    {
      "Key": {
        "PaletteType": "DMC",
        "ID": "3804",
        "Name": "Cyclamen Pink - Dark"
      },
      "Value": {
        "Argb": -3651981,
        "Hex": "C84673"
      }
    },
    {
      "Key": {
        "PaletteType": "DMC",
        "ID": "3805",
        "Name": "Cyclamen Pink"
      },
      "Value": {
        "Argb": -2795642,
        "Hex": "D55786"
      }
    },
    {
      "Key": {
        "PaletteType": "DMC",
        "ID": "3806",
        "Name": "Cyclamen Pink - Light"
      },
      "Value": {
        "Argb": -1933147,
        "Hex": "E280A5"
      }
    },
    {
      "Key": {
        "PaletteType": "DMC",
        "ID": "3807",
        "Name": "Cornflower Blue"
      },
      "Value": {
        "Argb": -9930069,
        "Hex": "687AAB"
      }
    },
    {
      "Key": {
        "PaletteType": "DMC",
        "ID": "3808",
        "Name": "Turquoise - Ultra Very Dark"
      },
      "Value": {
        "Argb": -14065301,
        "Hex": "29616B"
      }
    },
    {
      "Key": {
        "PaletteType": "DMC",
        "ID": "3809",
        "Name": "Turquoise - Very Dark"
      },
      "Value": {
        "Argb": -13665918,
        "Hex": "2F7982"
      }
    },
    {
      "Key": {
        "PaletteType": "DMC",
        "ID": "3810",
        "Name": "Turquoise - Dark"
      },
      "Value": {
        "Argb": -11298912,
        "Hex": "5397A0"
      }
    },
    {
      "Key": {
        "PaletteType": "DMC",
        "ID": "3811",
        "Name": "Turquoise - Very Light"
      },
      "Value": {
        "Argb": -5449257,
        "Hex": "ACD9D7"
      }
    },
    {
      "Key": {
        "PaletteType": "DMC",
        "ID": "3812",
        "Name": "Seagreen - Very Dark"
      },
      "Value": {
        "Argb": -16347007,
        "Hex": "069081"
      }
    },
    {
      "Key": {
        "PaletteType": "DMC",
        "ID": "3813",
        "Name": "Blue Green - Light"
      },
      "Value": {
        "Argb": -6437710,
        "Hex": "9DC4B2"
      }
    },
    {
      "Key": {
        "PaletteType": "DMC",
        "ID": "3814",
        "Name": "Aquamarine"
      },
      "Value": {
        "Argb": -13399434,
        "Hex": "338A76"
      }
    },
    {
      "Key": {
        "PaletteType": "DMC",
        "ID": "3815",
        "Name": "Celadon Green - Dark"
      },
      "Value": {
        "Argb": -11302291,
        "Hex": "538A6D"
      }
    },
    {
      "Key": {
        "PaletteType": "DMC",
        "ID": "3816",
        "Name": "Celadon Green"
      },
      "Value": {
        "Argb": -9328755,
        "Hex": "71A78D"
      }
    },
    {
      "Key": {
        "PaletteType": "DMC",
        "ID": "3817",
        "Name": "Celadon Green - Light"
      },
      "Value": {
        "Argb": -7160666,
        "Hex": "92BCA6"
      }
    },
    {
      "Key": {
        "PaletteType": "DMC",
        "ID": "3818",
        "Name": "Emerald Green - Ultra Very Dark"
      },
      "Value": {
        "Argb": -15439808,
        "Hex": "146840"
      }
    },
    {
      "Key": {
        "PaletteType": "DMC",
        "ID": "3819",
        "Name": "Moss Green - Light"
      },
      "Value": {
        "Argb": -3816881,
        "Hex": "C5C24F"
      }
    },
    {
      "Key": {
        "PaletteType": "DMC",
        "ID": "3820",
        "Name": "Straw - Dark"
      },
      "Value": {
        "Argb": -2509251,
        "Hex": "D9B63D"
      }
    },
    {
      "Key": {
        "PaletteType": "DMC",
        "ID": "3821",
        "Name": "Straw"
      },
      "Value": {
        "Argb": -1981356,
        "Hex": "E1C454"
      }
    },
    {
      "Key": {
        "PaletteType": "DMC",
        "ID": "3822",
        "Name": "Straw - Light"
      },
      "Value": {
        "Argb": -1452943,
        "Hex": "E9D471"
      }
    },
    {
      "Key": {
        "PaletteType": "DMC",
        "ID": "3823",
        "Name": "Yellow - Ultra Pale"
      },
      "Value": {
        "Argb": -1249851,
        "Hex": "ECEDC5"
      }
    },
    {
      "Key": {
        "PaletteType": "DMC",
        "ID": "3824",
        "Name": "Apricot - Light"
      },
      "Value": {
        "Argb": -607324,
        "Hex": "F6BBA4"
      }
    },
    {
      "Key": {
        "PaletteType": "DMC",
        "ID": "3825",
        "Name": "Pumpkin - Pale"
      },
      "Value": {
        "Argb": -673150,
        "Hex": "F5BA82"
      }
    },
    {
      "Key": {
        "PaletteType": "DMC",
        "ID": "3826",
        "Name": "Golden Brown"
      },
      "Value": {
        "Argb": -5081804,
        "Hex": "B27534"
      }
    },
    {
      "Key": {
        "PaletteType": "DMC",
        "ID": "3827",
        "Name": "Golden Brown - Pale"
      },
      "Value": {
        "Argb": -1394068,
        "Hex": "EABA6C"
      }
    },
    {
      "Key": {
        "PaletteType": "DMC",
        "ID": "3828",
        "Name": "Hazelnut Brown"
      },
      "Value": {
        "Argb": -4678307,
        "Hex": "B89D5D"
      }
    },
    {
      "Key": {
        "PaletteType": "DMC",
        "ID": "3829",
        "Name": "Old Gold - Very Dark"
      },
      "Value": {
        "Argb": -5863878,
        "Hex": "A6863A"
      }
    },
    {
      "Key": {
        "PaletteType": "DMC",
        "ID": "3830",
        "Name": "Terra Cotta"
      },
      "Value": {
        "Argb": -4823990,
        "Hex": "B6644A"
      }
    },
    {
      "Key": {
        "PaletteType": "DMC",
        "ID": "3831",
        "Name": "Raspberry - Dark"
      },
      "Value": {
        "Argb": -4831666,
        "Hex": "B6464E"
      }
    },
    {
      "Key": {
        "PaletteType": "DMC",
        "ID": "3832",
        "Name": "Raspberry - Medium"
      },
      "Value": {
        "Argb": -2858901,
        "Hex": "D4606B"
      }
    },
    {
      "Key": {
        "PaletteType": "DMC",
        "ID": "3833",
        "Name": "Raspberry - Light"
      },
      "Value": {
        "Argb": -1932147,
        "Hex": "E2848D"
      }
    },
    {
      "Key": {
        "PaletteType": "DMC",
        "ID": "3834",
        "Name": "Grape - Dark"
      },
      "Value": {
        "Argb": -9352864,
        "Hex": "714960"
      }
    },
    {
      "Key": {
        "PaletteType": "DMC",
        "ID": "3835",
        "Name": "Grape - Medium"
      },
      "Value": {
        "Argb": -6787957,
        "Hex": "986C8B"
      }
    },
    {
      "Key": {
        "PaletteType": "DMC",
        "ID": "3836",
        "Name": "Grape - Light"
      },
      "Value": {
        "Argb": -4615763,
        "Hex": "B991AD"
      }
    },
    {
      "Key": {
        "PaletteType": "DMC",
        "ID": "3837",
        "Name": "Lavender - Ultra Dark"
      },
      "Value": {
        "Argb": -7905893,
        "Hex": "875D9B"
      }
    },
    {
      "Key": {
        "PaletteType": "DMC",
        "ID": "3838",
        "Name": "Lavender Blue - Dark"
      },
      "Value": {
        "Argb": -9731138,
        "Hex": "6B83BE"
      }
    },
    {
      "Key": {
        "PaletteType": "DMC",
        "ID": "3839",
        "Name": "Lavender Blue - Medium"
      },
      "Value": {
        "Argb": -8217906,
        "Hex": "829ACE"
      }
    },
    {
      "Key": {
        "PaletteType": "DMC",
        "ID": "3840",
        "Name": "Lavender Blue - Light"
      },
      "Value": {
        "Argb": -5716763,
        "Hex": "A8C4E5"
      }
    },
    {
      "Key": {
        "PaletteType": "DMC",
        "ID": "3841",
        "Name": "Baby Blue - Pale"
      },
      "Value": {
        "Argb": -4663838,
        "Hex": "B8D5E2"
      }
    },
    {
      "Key": {
        "PaletteType": "DMC",
        "ID": "3842",
        "Name": "Wedgewood - Very Dark"
      },
      "Value": {
        "Argb": -13869177,
        "Hex": "2C5F87"
      }
    },
    {
      "Key": {
        "PaletteType": "DMC",
        "ID": "3843",
        "Name": "Electric Blue"
      },
      "Value": {
        "Argb": -16744759,
        "Hex": "007EC9"
      }
    },
    {
      "Key": {
        "PaletteType": "DMC",
        "ID": "3844",
        "Name": "Bright Turquoise - Dark"
      },
      "Value": {
        "Argb": -16740932,
        "Hex": "008DBC"
      }
    },
    {
      "Key": {
        "PaletteType": "DMC",
        "ID": "3845",
        "Name": "Bright Turquoise - Medium"
      },
      "Value": {
        "Argb": -16730663,
        "Hex": "00B5D9"
      }
    },
    {
      "Key": {
        "PaletteType": "DMC",
        "ID": "3846",
        "Name": "Bright Turquoise - Light"
      },
      "Value": {
        "Argb": -15219230,
        "Hex": "17C5E2"
      }
    },
    {
      "Key": {
        "PaletteType": "DMC",
        "ID": "3847",
        "Name": "Teal Green - Dark"
      },
      "Value": {
        "Argb": -14848154,
        "Hex": "1D6F66"
      }
    },
    {
      "Key": {
        "PaletteType": "DMC",
        "ID": "3848",
        "Name": "Teal Green - Medium"
      },
      "Value": {
        "Argb": -12808315,
        "Hex": "3C8F85"
      }
    },
    {
      "Key": {
        "PaletteType": "DMC",
        "ID": "3849",
        "Name": "Teal Green - Light"
      },
      "Value": {
        "Argb": -10245213,
        "Hex": "63ABA3"
      }
    },
    {
      "Key": {
        "PaletteType": "DMC",
        "ID": "3850",
        "Name": "Bright Green - Dark"
      },
      "Value": {
        "Argb": -15693975,
        "Hex": "108769"
      }
    },
    {
      "Key": {
        "PaletteType": "DMC",
        "ID": "3851",
        "Name": "Bright Green - Light"
      },
      "Value": {
        "Argb": -12013933,
        "Hex": "48AE93"
      }
    },
    {
      "Key": {
        "PaletteType": "DMC",
        "ID": "3852",
        "Name": "Straw - Very Dark"
      },
      "Value": {
        "Argb": -3431899,
        "Hex": "CBA225"
      }
    },
    {
      "Key": {
        "PaletteType": "DMC",
        "ID": "3853",
        "Name": "Autumn Gold - Dark"
      },
      "Value": {
        "Argb": -1864135,
        "Hex": "E38E39"
      }
    },
    {
      "Key": {
        "PaletteType": "DMC",
        "ID": "3854",
        "Name": "Autumn Gold - Medium"
      },
      "Value": {
        "Argb": -871588,
        "Hex": "F2B35C"
      }
    },
    {
      "Key": {
        "PaletteType": "DMC",
        "ID": "3855",
        "Name": "Autumn Gold - Light"
      },
      "Value": {
        "Argb": -993400,
        "Hex": "F0D788"
      }
    },
    {
      "Key": {
        "PaletteType": "DMC",
        "ID": "3856",
        "Name": "Mahogany - Ultra Very Light"
      },
      "Value": {
        "Argb": -1063283,
        "Hex": "EFC68D"
      }
    },
    {
      "Key": {
        "PaletteType": "DMC",
        "ID": "3857",
        "Name": "Rosewood - Dark"
      },
      "Value": {
        "Argb": -9025485,
        "Hex": "764833"
      }
    },
    {
      "Key": {
        "PaletteType": "DMC",
        "ID": "3858",
        "Name": "Rosewood - Medium"
      },
      "Value": {
        "Argb": -7381684,
        "Hex": "8F5D4C"
      }
    },
    {
      "Key": {
        "PaletteType": "DMC",
        "ID": "3859",
        "Name": "Rosewood - Light"
      },
      "Value": {
        "Argb": -4092554,
        "Hex": "C18D76"
      }
    },
    {
      "Key": {
        "PaletteType": "DMC",
        "ID": "3860",
        "Name": "Cocoa"
      },
      "Value": {
        "Argb": -7572121,
        "Hex": "8C7567"
      }
    },
    {
      "Key": {
        "PaletteType": "DMC",
        "ID": "3861",
        "Name": "Cocoa - Light"
      },
      "Value": {
        "Argb": -5794936,
        "Hex": "A79388"
      }
    },
    {
      "Key": {
        "PaletteType": "DMC",
        "ID": "3862",
        "Name": "Mocha Beige - Dark"
      },
      "Value": {
        "Argb": -7769524,
        "Hex": "89724C"
      }
    },
    {
      "Key": {
        "PaletteType": "DMC",
        "ID": "3863",
        "Name": "Mocha Beige - Medium"
      },
      "Value": {
        "Argb": -6059419,
        "Hex": "A38A65"
      }
    },
    {
      "Key": {
        "PaletteType": "DMC",
        "ID": "3864",
        "Name": "Mocha Beige - Light"
      },
      "Value": {
        "Argb": -3952240,
        "Hex": "C3B190"
      }
    },
    {
      "Key": {
        "PaletteType": "DMC",
        "ID": "3865",
        "Name": "Winter White"
      },
      "Value": {
        "Argb": -394504,
        "Hex": "F9FAF8"
      }
    },
    {
      "Key": {
        "PaletteType": "DMC",
        "ID": "3866",
        "Name": "Mocha Brown - Ultra Very Light"
      },
      "Value": {
        "Argb": -1841964,
        "Hex": "E3E4D4"
      }
    },
    {
      "Key": {
        "PaletteType": "DMC",
        "ID": "B5200",
        "Name": "Snow White"
      },
      "Value": {
        "Argb": -1,
        "Hex": "FFFFFF"
      }
    },
    {
      "Key": {
        "PaletteType": "DMC",
        "ID": "BLANC",
        "Name": "White"
      },
      "Value": {
        "Argb": -1,
        "Hex": "FFFFFF"
      }
    },
    {
      "Key": {
        "PaletteType": "DMC",
        "ID": "ECRU",
        "Name": "Ecru/off-white"
      },
      "Value": {
        "Argb": -1447468,
        "Hex": "E9E9D4"
      }
    }
  ]
}